{
	"info": {
		"_postman_id": "446ba12a-7c60-46e2-9bee-1a679647be2d",
		"name": "Product",
		"schema": "https://schema.getpostman.com/json/collection/v2.1.0/collection.json",
		"_exporter_id": "25127233"
	},
	"item": [
		{
			"name": "POST Product",
			"request": {
				"method": "POST",
				"header": [],
				"body": {
					"mode": "raw",
					"raw": "{\r\n    \"productName\": \"Intel I3 6th GEN\",\r\n    \"productPrice\": 15000,\r\n    \"productDesc\": \"PC Processor\",\r\n    \"categoryId\": 2\r\n}",
					"options": {
						"raw": {
							"language": "json"
						}
					}
				},
				"url": {
					"raw": "http://localhost:8080/maamonoshatelecom/product/save",
					"protocol": "http",
					"host": [
						"localhost"
					],
					"port": "8080",
					"path": [
						"maamonoshatelecom",
						"product",
						"save"
					]
				}
			},
			"response": []
		},
		{
			"name": "GET Product",
			"request": {
				"method": "GET",
				"header": [],
				"url": {
					"raw": "http://localhost:8080/maamonoshatelecom/product/get",
					"protocol": "http",
					"host": [
						"localhost"
					],
					"port": "8080",
					"path": [
						"maamonoshatelecom",
						"product",
						"get"
					]
				}
			},
			"response": []
		},
		{
			"name": "DELETE Product",
			"request": {
				"method": "DELETE",
				"header": [],
				"url": {
					"raw": "http://localhost:8080/maamonoshatelecom/product/delete?id=1",
					"protocol": "http",
					"host": [
						"localhost"
					],
					"port": "8080",
					"path": [
						"maamonoshatelecom",
						"product",
						"delete"
					],
					"query": [
						{
							"key": "id",
							"value": "1"
						}
					]
				}
			},
			"response": []
		},
		{
			"name": "PUT Product",
			"request": {
				"method": "PUT",
				"header": [],
				"body": {
					"mode": "raw",
					"raw": "{\r\n\t\"productName\":\"Sumsang S12\",\r\n\t\"productPrice\":5000,\r\n\t\"productDesc\":\"This is SUMSANG Mobile\",\r\n\t\"categoryId\":2\r\n}",
					"options": {
						"raw": {
							"language": "json"
						}
					}
				},
				"url": {
					"raw": "http://localhost:8080/maamonoshatelecom/product/update?id=1",
					"protocol": "http",
					"host": [
						"localhost"
					],
					"port": "8080",
					"path": [
						"maamonoshatelecom",
						"product",
						"update"
					],
					"query": [
						{
							"key": "id",
							"value": "1"
						}
					]
				}
			},
			"response": []
		},
		{
			"name": "GET Product-by-categoryID",
			"request": {
				"method": "GET",
				"header": [],
				"url": {
					"raw": "http://localhost:8080/maamonoshatelecom/product/get-product-by-cid?id=2",
					"protocol": "http",
					"host": [
						"localhost"
					],
					"port": "8080",
					"path": [
						"maamonoshatelecom",
						"product",
						"get-product-by-cid"
					],
					"query": [
						{
							"key": "id",
							"value": "2"
						}
					]
				}
			},
			"response": []
		}
	]
}